gamingonlinux_rss-0.2.0.dist-info/METADATA
gamingonlinux_rss-0.2.0.dist-info/WHEEL
gamingonlinux_rss-0.2.0.dist-info/entry_points.txt
gamingonlinux_rss-0.2.0.dist-info/licenses/LICENSE
gamingonlinux_rss/__init__.py
gamingonlinux_rss/entrypoints/__init__.py
gamingonlinux_rss/entrypoints/cli.py
gamingonlinux_rss/exceptions.py
gamingonlinux_rss/model.py
gamingonlinux_rss/py.typed
gamingonlinux_rss/services.py
gamingonlinux_rss/templates/rss.xml.j2
gamingonlinux_rss/version.py
gamingonlinux_rss-0.2.0.dist-info/RECORD
