Metadata-Version: 2.1
Name: gamingonlinux-rss
Version: 0.2.0
Summary: Full article RSS of the GamingOnLinux website
Home-page: https://github.com/lyz-code/gamingonlinux-rss
Author-Email: Lyz <lyz-code-security-advisories@riseup.net>
License: GPL-3.0-only
Classifier: Development Status :: 2 - Pre-Alpha
Classifier: Intended Audience :: Developers
Classifier: License :: OSI Approved :: GNU General Public License v3 (GPLv3)
Classifier: Operating System :: Unix
Classifier: Operating System :: POSIX
Classifier: Programming Language :: Python
Classifier: Programming Language :: Python :: 3
Classifier: Programming Language :: Python :: 3.8
Classifier: Programming Language :: Python :: 3.9
Classifier: Programming Language :: Python :: 3.10
Classifier: Programming Language :: Python :: 3.11
Classifier: Topic :: Utilities
Classifier: Natural Language :: English
Project-URL: Issues, https://github.com/lyz-code/gamingonlinux-rss/issues
Project-URL: Homepage, https://github.com/lyz-code/gamingonlinux-rss
Project-URL: Documentation, https://lyz-code.github.io/gamingonlinux-rss
Requires-Python: >=3.8
Requires-Dist: beautifulsoup4>=4.11.1
Requires-Dist: tenacity>=8.0.1
Requires-Dist: pydantic!=1.10.0,!=1.10.1,>=1.9.1
Requires-Dist: jinja2>=3.1.2
Requires-Dist: click>=8.1.3
Requires-Dist: python-dateutil>=2.8.2
Requires-Dist: requests>=2.28.0
